{
  "alias_types_count": 0,
  "by_kind": {
    "enum": 16,
    "struct": 23
  },
  "eq_impls_total": 0,
  "files_scanned": 408,
  "have_derive_eq_or_partialeq_count": 0,
  "have_partialeq_or_eq_impl_count": 0,
  "have_view_impl": [],
  "have_view_impl_count": 0,
  "l1_l2_l3_uncovered_count": 39,
  "l1_l2_l3_uncovered_top50": [
    "Arch",
    "ArchExec",
    "ArchLayer",
    "ArchLayerExec",
    "Constants",
    "Core",
    "CoreState",
    "Directory",
    "DoShootdown",
    "Flags",
    "GPDE",
    "History",
    "Lbl",
    "LoadResult",
    "MemOp",
    "MemRegion",
    "MemRegionExec",
    "NodeEntry",
    "OpArgs",
    "PDE",
    "PTDir",
    "PTE",
    "PTMem",
    "Polarity",
    "Progress",
    "RLbl",
    "ShootdownVector",
    "State",
    "Step",
    "StoreResult",
    "ThreadState",
    "TokState",
    "Token",
    "Walk",
    "WalkResult",
    "WrappedMapToken",
    "WrappedTokenView",
    "WrappedUnmapToken",
    "Writes"
  ],
  "parse_errors": [],
  "total_defined_types": 39,
  "view_impls_total": 0
}